llm_dispatcher/__init__.py
llm_dispatcher/exceptions.py
llm_dispatcher/benchmarks/__init__.py
llm_dispatcher/benchmarks/analysis.py
llm_dispatcher/benchmarks/benchmark_analyzer.py
llm_dispatcher/benchmarks/benchmark_reporter.py
llm_dispatcher/benchmarks/benchmark_runner.py
llm_dispatcher/benchmarks/cost_benchmark.py
llm_dispatcher/benchmarks/custom_benchmark.py
llm_dispatcher/benchmarks/evaluation.py
llm_dispatcher/benchmarks/performance_benchmark.py
llm_dispatcher/benchmarks/quality_benchmark.py
llm_dispatcher/benchmarks/reports.py
llm_dispatcher/benchmarks/utils.py
llm_dispatcher/benchmarks/utils/__init__.py
llm_dispatcher/caching/__init__.py
llm_dispatcher/caching/cache_manager.py
llm_dispatcher/caching/semantic_cache.py
llm_dispatcher/config/__init__.py
llm_dispatcher/config/config_loader.py
llm_dispatcher/config/settings.py
llm_dispatcher/core/__init__.py
llm_dispatcher/core/base.py
llm_dispatcher/core/switch_engine.py
llm_dispatcher/decorators/__init__.py
llm_dispatcher/decorators/switch_decorator.py
llm_dispatcher/monitoring/__init__.py
llm_dispatcher/monitoring/alerting.py
llm_dispatcher/monitoring/analytics.py
llm_dispatcher/monitoring/dashboard.py
llm_dispatcher/monitoring/metrics_collector.py
llm_dispatcher/multimodal/__init__.py
llm_dispatcher/multimodal/audio_processor.py
llm_dispatcher/multimodal/image_processor.py
llm_dispatcher/multimodal/media_validator.py
llm_dispatcher/multimodal/multimodal_analyzer.py
llm_dispatcher/providers/__init__.py
llm_dispatcher/providers/anthropic_provider.py
llm_dispatcher/providers/base_provider.py
llm_dispatcher/providers/google_provider.py
llm_dispatcher/providers/grok_provider.py
llm_dispatcher/providers/openai_provider.py
llm_dispatcher/utils/__init__.py
llm_dispatcher/utils/benchmark_manager.py
llm_dispatcher/utils/cost_calculator.py
llm_dispatcher/utils/performance_monitor.py
llm_dispatcher/utils/task_classifier.py
llm_dispatcher/utils/token_counter.py
llm_dispatcher-1.0.0.dist-info/licenses/LICENSE
llm_dispatcher-1.0.0.dist-info/METADATA
llm_dispatcher-1.0.0.dist-info/WHEEL
llm_dispatcher-1.0.0.dist-info/top_level.txt
llm_dispatcher-1.0.0.dist-info/RECORD
