Metadata-Version: 2.4
Name: llm-dispatcher
Version: 1.0.0
Summary: Intelligent LLM dispatching with performance-based routing, multimodal support, streaming, monitoring, and comprehensive analytics
Home-page: https://github.com/ashhadahsan/llm-dispatcher
Author: ashhadahsan
Author-email: ashhadahsan <ashhadahsan@gmail.com>
License: MIT
Project-URL: Homepage, https://github.com/ashhadahsan/llm-dispatcher
Project-URL: Repository, https://github.com/ashhadahsan/llm-dispatcher
Project-URL: Documentation, https://llm-dispatcher.readthedocs.io
Project-URL: Bug Tracker, https://github.com/ashhadahsan/llm-dispatcher/issues
Keywords: llm,ai,openai,anthropic,google,machine-learning,nlp,routing,dispatch,multimodal,streaming,monitoring,analytics,caching
Classifier: Development Status :: 3 - Alpha
Classifier: Intended Audience :: Developers
Classifier: Intended Audience :: Science/Research
Classifier: Operating System :: OS Independent
Classifier: Programming Language :: Python :: 3
Classifier: Programming Language :: Python :: 3.8
Classifier: Programming Language :: Python :: 3.9
Classifier: Programming Language :: Python :: 3.10
Classifier: Programming Language :: Python :: 3.11
Classifier: Programming Language :: Python :: 3.12
Classifier: Topic :: Scientific/Engineering :: Artificial Intelligence
Classifier: Topic :: Software Development :: Libraries :: Python Modules
Classifier: Topic :: Text Processing :: Linguistic
Classifier: Topic :: Internet :: WWW/HTTP :: Dynamic Content
Requires-Python: >=3.8
License-File: LICENSE
Requires-Dist: pydantic>=2.0.0
Requires-Dist: requests>=2.31.0
Requires-Dist: aiohttp>=3.8.0
Requires-Dist: tenacity>=8.0.0
Requires-Dist: openai>=1.0.0
Requires-Dist: anthropic>=0.7.0
Requires-Dist: google-generativeai>=0.3.0
Requires-Dist: tiktoken>=0.5.0
Requires-Dist: pillow>=9.0.0
Requires-Dist: pydub>=0.25.0
Requires-Dist: numpy>=1.21.0
Requires-Dist: datasets>=2.0.0
Requires-Dist: evaluate>=0.4.0
Requires-Dist: rouge-score>=0.1.2
Requires-Dist: sacrebleu>=2.3.0
Requires-Dist: bert-score>=0.3.13
Requires-Dist: pyyaml>=6.0
Requires-Dist: python-dotenv>=1.0.0
Requires-Dist: asyncio-mqtt>=0.11.0
Requires-Dist: redis>=4.5.0
Requires-Dist: sqlalchemy>=2.0.0
Requires-Dist: alembic>=1.11.0
Requires-Dist: bcrypt>=4.0.0
Requires-Dist: cryptography>=41.0.0
Requires-Dist: tqdm>=4.0.0
Requires-Dist: regex>=2022.1.18
Requires-Dist: charset-normalizer>=2.0.0
Requires-Dist: urllib3>=1.21.1
Requires-Dist: certifi>=2017.4.17
Requires-Dist: anyio>=3.5.0
Requires-Dist: distro>=1.7.0
Requires-Dist: httpx>=0.23.0
Requires-Dist: jiter>=0.4.0
Requires-Dist: sniffio
Requires-Dist: typing-extensions>=4.11.0
Requires-Dist: annotated-types>=0.6.0
Requires-Dist: pydantic-core>=2.33.0
Requires-Dist: typing-inspection>=0.4.0
Requires-Dist: idna>=2.8
Requires-Dist: docstring-parser>=0.15.0
Requires-Dist: google-ai-generativelanguage>=0.6.15
Requires-Dist: google-api-core>=2.25.0
Requires-Dist: google-api-python-client>=2.182.0
Requires-Dist: google-auth>=2.15.0
Requires-Dist: protobuf>=5.29.0
Requires-Dist: proto-plus>=1.22.3
Requires-Dist: googleapis-common-protos>=1.56.2
Requires-Dist: grpcio>=1.33.2
Requires-Dist: grpcio-status>=1.33.2
Requires-Dist: cachetools>=2.0.0
Requires-Dist: pyasn1-modules>=0.2.1
Requires-Dist: rsa>=3.1.4
Requires-Dist: pyasn1>=0.1.3
Requires-Dist: httplib2>=0.19.0
Requires-Dist: google-auth-httplib2>=0.2.0
Requires-Dist: uritemplate>=3.0.1
Requires-Dist: pyparsing>=3.0.4
Requires-Dist: librosa>=0.9.0
Requires-Dist: soundfile>=0.12.0
Requires-Dist: ragas>=0.1.0
Requires-Dist: langchain>=0.1.0
Requires-Dist: langchain-openai>=0.1.0
Requires-Dist: langchain-anthropic>=0.1.0
Requires-Dist: langchain-google-genai>=0.1.0
Requires-Dist: sentence-transformers>=2.2.0
Requires-Dist: scikit-learn>=1.3.0
Requires-Dist: matplotlib>=3.7.0
Requires-Dist: seaborn>=0.12.0
Requires-Dist: plotly>=5.15.0
Provides-Extra: dev
Requires-Dist: pytest>=7.0.0; extra == "dev"
Requires-Dist: pytest-asyncio>=0.21.0; extra == "dev"
Requires-Dist: pytest-cov>=4.0.0; extra == "dev"
Requires-Dist: black>=23.0.0; extra == "dev"
Requires-Dist: isort>=5.12.0; extra == "dev"
Requires-Dist: flake8>=6.0.0; extra == "dev"
Requires-Dist: pre-commit>=3.0.0; extra == "dev"
Requires-Dist: jupyter>=1.0.0; extra == "dev"
Requires-Dist: ipykernel>=6.0.0; extra == "dev"
Provides-Extra: docs
Requires-Dist: mkdocs>=1.5.0; extra == "docs"
Requires-Dist: mkdocs-material>=9.4.0; extra == "docs"
Requires-Dist: mkdocs-minify-plugin>=0.7.0; extra == "docs"
Requires-Dist: mkdocs-git-revision-date-localized-plugin>=1.2.0; extra == "docs"
Requires-Dist: mkdocs-social-plugin>=0.1.0; extra == "docs"
Provides-Extra: benchmark
Requires-Dist: transformers>=4.30.0; extra == "benchmark"
Requires-Dist: torch>=2.0.0; extra == "benchmark"
Requires-Dist: accelerate>=0.20.0; extra == "benchmark"
Requires-Dist: datasets>=2.0.0; extra == "benchmark"
Requires-Dist: evaluate>=0.4.0; extra == "benchmark"
Dynamic: author
Dynamic: home-page
Dynamic: license-file
Dynamic: requires-python
